{
  "hash": "e7465c241da9a12ced801394ee63311f",
  "result": {
    "engine": "knitr",
    "markdown": "---\ntitle: \"Gráfico de puntos con intervalos de confianza\"\nauthor: \"Richard Pardes-Espinosa\"\ndata: \"2024-03-20\"\nformat: html\neditor: visual\neditor_options: \n  chunk_output_type: console\ntoc: true\nnumber-sections: true\ncode-fold: show\ncode-summary: \"ver código\"\n---\n\n\n\n## Importar datos\n\nUsando la función **tibble::tribble** se importa los datos de manera rápida. La base contiene a los tratamientos \n\n\n::: {.cell}\n\n```{.r .cell-code}\nlibrary(tidyverse)\n\n# Crear el dataframe con los datos proporcionados\ndato <- tibble::tribble(\n  ~trat, ~peso, ~germ,\n  \"esc\",  \"p1\",   60,\n  \"esc\",  \"p2\",   55,\n  \"esc\",  \"p3\",   45,\n  \"esc\",  \"p4\",   50,\n  \"esc\",  \"p5\",   65,\n  \"esc\",  \"p6\",   55,\n  \"esc\",  \"p7\",   55,\n  \"esc\",  \"p8\",   50,\n  \"esc\",  \"p9\",   40,\n  \"esc\", \"p10\",   45,\n  \"eschorm\",  \"p1\",   80,\n  \"eschorm\",  \"p2\",   75,\n  \"eschorm\",  \"p3\",   70,\n  \"eschorm\",  \"p4\",  100,\n  \"eschorm\",  \"p5\",   70,\n  \"eschorm\",  \"p6\",   75,\n  \"eschorm\",  \"p7\",   70,\n  \"eschorm\",  \"p8\",   65,\n  \"eschorm\",  \"p9\",   95,\n  \"eschorm\", \"p10\",   90,\n  \"horm\",  \"p1\",   60,\n  \"horm\",  \"p2\",   25,\n  \"horm\",  \"p3\",   15,\n  \"horm\",  \"p4\",   20,\n  \"horm\",  \"p5\",   10,\n  \"horm\",  \"p6\",   15,\n  \"horm\",  \"p7\",   55,\n  \"horm\",  \"p8\",    0,\n  \"horm\",  \"p9\",   15,\n  \"horm\", \"p10\",   10\n)\ndato\n```\n\n::: {.cell-output .cell-output-stdout}\n\n```\n# A tibble: 30 × 3\n   trat  peso   germ\n   <chr> <chr> <dbl>\n 1 esc   p1       60\n 2 esc   p2       55\n 3 esc   p3       45\n 4 esc   p4       50\n 5 esc   p5       65\n 6 esc   p6       55\n 7 esc   p7       55\n 8 esc   p8       50\n 9 esc   p9       40\n10 esc   p10      45\n# ℹ 20 more rows\n```\n\n\n:::\n:::\n\n\n## Visualización de gráfico\n\nDespués de carga la librería `ggplot2` se procede a definir la función `mean_cl_boot` que calcula la media y el intervalo de confianza del 95% usando la fórmula `1.96 * error estándar`. A continuación, se emplea `ggplot` para crear un gráfico donde se mapea el eje x (`trat`), el eje y (`germ`) y el color de relleno (`trat`). La función `stat_summary` se usa con `fun.data = mean_cl_boot` y `geom = \"pointrange\"` para agregar puntos con barras de error. Se aplica `theme_minimal` para un tema limpio y `scale_y_continuous` para definir los puntos de interrupción en el eje y. Las etiquetas de los ejes se configuran con `labs`, y `theme` ajusta el tamaño y color del texto de los ejes y elimina la leyenda.\n\n\n\n::: {.cell}\n\n```{.r .cell-code}\n# Cargar librería\nlibrary(ggplot2)\n\n# Media e intervalos de confianza al 95%\nmean_cl_boot <- function(x) {\n  m <- mean(x, na.rm = TRUE)\n  se <- sd(x, na.rm = TRUE) / sqrt(length(x))\n  ymin <- m - 1.96 * se  # Intervalo de confianza al 95%\n  ymax <- m + 1.96 * se  # Intervalo de confianza al 95%\n  return(c(y = m, ymin = ymin, ymax = ymax))\n}\n\n# Gráfico con intervalos de confianza\ndato |> \n  ggplot(aes(x = trat, \n             y = germ, \n             fill = trat)) +\n  stat_summary(fun.data = mean_cl_boot, \n               geom = \"pointrange\", \n               size = 0.8) +\n  theme_minimal() +\n  scale_y_continuous(breaks = c(0,20,40,60,80,100)) +\n  labs(x = \"Tratamientos\", \n       y = \"Germinación (%)\") + \n  theme(axis.text.x = element_text(size = 12, \n                                   color = \"black\", \n                                   hjust = 1),\n        axis.text.y = element_text(size = 12, \n                                   color = \"black\"),\n        axis.title = element_text(size = 14, \n                                  color = \"black\"),\n        legend.position = \"none\")\n```\n\n::: {.cell-output-display}\n![](12_files/figure-html/unnamed-chunk-2-1.png){width=672}\n:::\n:::\n",
    "supporting": [
      "12_files"
    ],
    "filters": [
      "rmarkdown/pagebreak.lua"
    ],
    "includes": {},
    "engineDependencies": {},
    "preserve": {},
    "postProcess": true
  }
}